eririn/__init__.py
eririn/__main__.py
eririn/conv.py
eririn-0.2.114.dist-info/LICENSE
eririn-0.2.114.dist-info/METADATA
eririn-0.2.114.dist-info/WHEEL
eririn-0.2.114.dist-info/entry_points.txt
eririn-0.2.114.dist-info/top_level.txt
eririn-0.2.114.dist-info/RECORD
