Metadata-Version: 2.1
Name: eririn
Version: 0.2.114
Summary: Generate Excel Graph Paper sheets from image files
Home-page: https://github.com/kimrin/eririn
Author: Takeshi Kimura
Author-email: kittykimura@gmail.com
License: UNKNOWN
Project-URL: Bug Reports, https://github.com/kimrin/eririn/issues
Project-URL: Funding, https://donate.pypi.org
Project-URL: Say Thanks!, https://twitter.com/kimrin/
Project-URL: Source, https://github.com/kimrin/eririn/
Keywords: openpyxl Pillow Excel
Platform: UNKNOWN
Classifier: Development Status :: 3 - Alpha
Classifier: Intended Audience :: Developers
Classifier: Topic :: Office/Business :: Financial :: Spreadsheet
Classifier: License :: OSI Approved :: MIT License
Classifier: Programming Language :: Python :: 3
Classifier: Programming Language :: Python :: 3.5
Classifier: Programming Language :: Python :: 3.6
Classifier: Programming Language :: Python :: 3.7
Classifier: Programming Language :: Python :: 3.8
Classifier: Programming Language :: Python :: 3 :: Only
Requires-Python: >=3.5, <4
Requires-Dist: openpyxl
Requires-Dist: Pillow
Requires-Dist: scikit-learn
Requires-Dist: docopt
Requires-Dist: tqdm
Provides-Extra: dev
Provides-Extra: test
